arbiter3/__init__.py
arbiter3/arbiter/__init__.py
arbiter3/arbiter/admin.py
arbiter3/arbiter/apps.py
arbiter3/arbiter/conf.py
arbiter3/arbiter/email.py
arbiter3/arbiter/eval.py
arbiter3/arbiter/fixtures/default_policy.json
arbiter3/arbiter/management/__init__.py
arbiter3/arbiter/management/commands/__init__.py
arbiter3/arbiter/management/commands/clean.py
arbiter3/arbiter/management/commands/evaluate.py
arbiter3/arbiter/management/commands/test_email.py
arbiter3/arbiter/management/commands/test_lookup.py
arbiter3/arbiter/migrations/0001_initial.py
arbiter3/arbiter/migrations/0002_policy_is_active.py
arbiter3/arbiter/migrations/0002_rename_last_applied_target_limits.py
arbiter3/arbiter/migrations/0003_remove_policy_is_active_policy_active.py
arbiter3/arbiter/migrations/0004_merge_20241114_1237.py
arbiter3/arbiter/migrations/0005_remove_target_unique_target_target_port_and_more.py
arbiter3/arbiter/migrations/0006_arbuser.py
arbiter3/arbiter/migrations/0007_policy_watcher_mode.py
arbiter3/arbiter/migrations/0008_refresh_queries.py
arbiter3/arbiter/migrations/0009_alter_policy_options_alter_policy_description_and_more.py
arbiter3/arbiter/migrations/0010_alter_policy_options.py
arbiter3/arbiter/migrations/__init__.py
arbiter3/arbiter/models.py
arbiter3/arbiter/plots.py
arbiter3/arbiter/promclient.py
arbiter3/arbiter/prop.py
arbiter3/arbiter/query.py
arbiter3/arbiter/templates/arbiter/add_policy.html
arbiter3/arbiter/templates/arbiter/base.html
arbiter3/arbiter/templates/arbiter/basepolicy_list.html
arbiter3/arbiter/templates/arbiter/change_view.html
arbiter3/arbiter/templates/arbiter/dashboard.html
arbiter3/arbiter/templates/arbiter/email_body.html
arbiter3/arbiter/templates/arbiter/email_subject.html
arbiter3/arbiter/templates/arbiter/graph.html
arbiter3/arbiter/templates/arbiter/navbar.html
arbiter3/arbiter/templates/arbiter/penalty_widget.html
arbiter3/arbiter/templates/arbiter/usagepolicy_change.html
arbiter3/arbiter/templates/arbiter/usagepolicy_list.html
arbiter3-0.0.11.dist-info/LICENSE
arbiter3-0.0.11.dist-info/METADATA
arbiter3-0.0.11.dist-info/WHEEL
arbiter3-0.0.11.dist-info/entry_points.txt
arbiter3-0.0.11.dist-info/RECORD
