Metadata-Version: 2.3
Name: arbiter3
Version: 0.0.11
Summary: 
Author: Kai Forrest
Author-email: kai.forrest@utah.edu
Requires-Python: >=3.11,<4.0
Classifier: Programming Language :: Python :: 3
Classifier: Programming Language :: Python :: 3.11
Classifier: Programming Language :: Python :: 3.12
Classifier: Programming Language :: Python :: 3.13
Requires-Dist: aiohttp (>=3.9.1,<4.0.0)
Requires-Dist: asyncio (>=3.4.3,<4.0.0)
Requires-Dist: django (>=5.0.0,<6.0.0)
Requires-Dist: gunicorn (>=23.0.0,<24.0.0)
Requires-Dist: jinja2 (>=3.1.5,<4.0.0)
Requires-Dist: kaleido (==0.2.1)
Requires-Dist: plotly (>=5.20.0,<6.0.0)
Requires-Dist: prometheus-api-client (>=0.5.3,<0.6.0)
Requires-Dist: requests (>=2.31.0,<3.0.0)
